root_signature/__init__.py
root_signature-0.1.1.dist-info/DESCRIPTION.rst
root_signature-0.1.1.dist-info/METADATA
root_signature-0.1.1.dist-info/RECORD
root_signature-0.1.1.dist-info/WHEEL
root_signature-0.1.1.dist-info/metadata.json
root_signature-0.1.1.dist-info/top_level.txt
