Metadata-Version: 2.0
Name: root-signature
Version: 0.1.1
Summary: Extract data from root_files
Home-page: http://github.com/zderev/root_signature
Author: Igor Zderev
Author-email: qbeat@bk.ru
License: MIT
Platform: UNKNOWN
